packshim/__init__.py
packshim/random_f.py
packshim-0.0.2.dist-info/METADATA
packshim-0.0.2.dist-info/WHEEL
packshim-0.0.2.dist-info/top_level.txt
packshim-0.0.2.dist-info/RECORD
